gt2.vhdl
library ieee;
use ieee.std_logic_1164.all;

entity gt2 is
    port(
        a,b: in std_logic_vector(1 downto 0);
        y: out std_logic
    );
end gt2;

architecture behav of gt2 is
    signal p0, p1, p2, p3: std_logic;
begin
    y <= p0 or p1 or p2;

    p0 <= a(1) and (not b(1));
    p1 <= a(0) and (not b(1)) and (not b(0));
    p2 <= a(0) and a(1) and (not b(0));
end behav;

gt2_tb.vhdl
library ieee;
use ieee.std_logic_1164.all;

entity gt2_tb is
    end gt2_tb;

architecture tb_behav of gt2_tb is
    signal test_in0, test_in1: std_logic_vector(1 downto 0);
    signal test_out: std_logic;
begin
    uut: entity work.gt2(behav)
        port map(
            a=> test_in0,
            b=> test_in1,
            y=>test_out
        );
process 
begin

    test_in0<= "00";
    test_in1<= "00";
    wait for 200 ns;

    test_in0<= "00";
    test_in1<= "01";
    wait for 200 ns;

    test_in0<= "00";
    test_in1<= "10";
    wait for 200 ns;

    test_in0<= "00";
    test_in1<= "11";
    wait for 200 ns;

    test_in0<= "01";
    test_in1<= "00";
    wait for 200 ns;

    test_in0<= "01";
    test_in1<= "01";
    wait for 200 ns;

    test_in0<= "01";
    test_in1<= "10";
    wait for 200 ns;

    test_in0<= "01";
    test_in1<= "11";
    wait for 200 ns;

    test_in0<= "10";
    test_in1<= "00";
    wait for 200 ns;

    test_in0<= "10";
    test_in1<= "01";
    wait for 200 ns;

    test_in0<= "10";
    test_in1<= "10";
    wait for 200 ns;

    test_in0<= "10";
    test_in1<= "11";
    wait for 200 ns;

    test_in0<= "11";
    test_in1<= "00";
    wait for 200 ns;

    test_in0<= "11";
    test_in1<= "01";
    wait for 200 ns;

    test_in0<= "11";
    test_in1<= "10";
    wait for 200 ns;

    test_in0<= "11";
    test_in1<= "11";
    wait for 200 ns;
    wait;

end process;
end tb_behav;

gt2.vcd
$date
  Tue Dec 20 15:57:43 2022
$end
$version
  GHDL v0
$end
$timescale
  1 fs
$end
$scope module standard $end
$upscope $end
$scope module std_logic_1164 $end
$upscope $end
$scope module gt2_tb $end
$var reg 2 ! test_in0[1:0] $end
$var reg 2 " test_in1[1:0] $end
$var reg 1 # test_out $end
$scope module uut $end
$var reg 2 $ a[1:0] $end
$var reg 2 % b[1:0] $end
$var reg 1 & y $end
$var reg 1 ' p0 $end
$var reg 1 ( p1 $end
$var reg 1 ) p2 $end
$var reg 1 * p3 $end
$upscope $end
$upscope $end
$enddefinitions $end
#0
b00 !
b00 "
0#
b00 $
b00 %
0&
0'
0(
0)
U*
#200000000
b01 "
b01 %
#400000000
b10 "
b10 %
#600000000
b11 "
b11 %
#800000000
b01 !
b00 "
1#
b01 $
b00 %
1&
1(
#1000000000
b01 "
0#
b01 %
0&
0(
#1200000000
b10 "
b10 %
#1400000000
b11 "
b11 %
#1600000000
b10 !
b00 "
1#
b10 $
b00 %
1&
1'
#1800000000
b01 "
b01 %
#2000000000
b10 "
0#
b10 %
0&
0'
#2200000000
b11 "
b11 %
#2400000000
b11 !
b00 "
1#
b11 $
b00 %
1&
1'
1(
1)
#2600000000
b01 "
b01 %
0(
0)
#2800000000
b10 "
b10 %
0'
1)
#3000000000
b11 "
0#
b11 %
0&
0)
